pichondria/__init__.py
pichondria/pichondria.py
pichondria-1.0.2.dist-info/LICENSE
pichondria-1.0.2.dist-info/METADATA
pichondria-1.0.2.dist-info/WHEEL
pichondria-1.0.2.dist-info/top_level.txt
pichondria-1.0.2.dist-info/RECORD
