Metadata-Version: 2.1
Name: pichondria
Version: 1.0.2
Summary: Pichondria library is the official library to communicate with Pichondria UPS HAT for RaspberryPi over I2C. https://pichondria.com 
Home-page: https://github.com/pichondria/pichondria
Author: John KG, Pichondria
Author-email: pichondria@gmail.com
Keywords: Python,Pichondria,UPS,UPS HAT,Pichondria UPS,RaspberryPi,RPi
Classifier: Programming Language :: Python :: 3
Classifier: License :: OSI Approved :: MIT License
Classifier: Operating System :: OS Independent
Requires-Python: >=3.6
License-File: LICENSE
Requires-Dist: smbus
